{
  "source": "harga-emas.org",
  "url": "https://harga-emas.org",
  "scrapedAt": "2026-02-17T18:50:42.533Z",
  "updateTime": "17 Februari 2026",
  "buybackPrice": {
    "price": 2761200,
    "priceFormatted": "Rp 2.761.200",
    "type": "Buyback per gram"
  },
  "antam": [
    {
      "weight": 100,
      "weightUnit": "gram",
      "type": "Antam 100g",
      "sellPrice": 285921000,
      "sellPriceFormatted": "Rp 285.921.000",
      "pricePerGram": 2859210,
      "pricePerGramFormatted": "Rp 2.859.210/gram"
    },
    {
      "weight": 50,
      "weightUnit": "gram",
      "type": "Antam 50g",
      "sellPrice": 143450000,
      "sellPriceFormatted": "Rp 143.450.000",
      "pricePerGram": 2869000,
      "pricePerGramFormatted": "Rp 2.869.000/gram"
    },
    {
      "weight": 25,
      "weightUnit": "gram",
      "type": "Antam 25g",
      "sellPrice": 71859000,
      "sellPriceFormatted": "Rp 71.859.000",
      "pricePerGram": 2874360,
      "pricePerGramFormatted": "Rp 2.874.360/gram"
    },
    {
      "weight": 10,
      "weightUnit": "gram",
      "type": "Antam 10g",
      "sellPrice": 28791000,
      "sellPriceFormatted": "Rp 28.791.000",
      "pricePerGram": 2879100,
      "pricePerGramFormatted": "Rp 2.879.100/gram"
    },
    {
      "weight": 7,
      "weightUnit": "gram",
      "type": "Antam 7g",
      "sellPrice": 29680000,
      "sellPriceFormatted": "Rp 29.680.000",
      "pricePerGram": 4240000,
      "pricePerGramFormatted": "Rp 4.240.000/gram"
    },
    {
      "weight": 5,
      "weightUnit": "gram",
      "type": "Antam 5g",
      "sellPrice": 14467000,
      "sellPriceFormatted": "Rp 14.467.000",
      "pricePerGram": 2893400,
      "pricePerGramFormatted": "Rp 2.893.400/gram"
    },
    {
      "weight": 4,
      "weightUnit": "gram",
      "type": "Antam 4g",
      "sellPrice": 11658500,
      "sellPriceFormatted": "Rp 11.658.500",
      "pricePerGram": 2914625,
      "pricePerGramFormatted": "Rp 2.914.625/gram"
    },
    {
      "weight": 3,
      "weightUnit": "gram",
      "type": "Antam 3g",
      "sellPrice": 8761500,
      "sellPriceFormatted": "Rp 8.761.500",
      "pricePerGram": 2920500,
      "pricePerGramFormatted": "Rp 2.920.500/gram"
    },
    {
      "weight": 2,
      "weightUnit": "gram",
      "type": "Antam 2g",
      "sellPrice": 7160000,
      "sellPriceFormatted": "Rp 7.160.000",
      "pricePerGram": 3580000,
      "pricePerGramFormatted": "Rp 3.580.000/gram"
    },
    {
      "weight": 1,
      "weightUnit": "gram",
      "type": "Antam 1g",
      "sellPrice": 3580000,
      "sellPriceFormatted": "Rp 3.580.000",
      "pricePerGram": 3580000,
      "pricePerGramFormatted": "Rp 3.580.000/gram"
    },
    {
      "weight": 0.5,
      "weightUnit": "gram",
      "type": "Antam 0.5g",
      "sellPrice": 1562500,
      "sellPriceFormatted": "Rp 1.562.500",
      "pricePerGram": 3125000,
      "pricePerGramFormatted": "Rp 3.125.000/gram"
    },
    {
      "weight": 0.25,
      "weightUnit": "gram",
      "type": "Antam 0.25g",
      "sellPrice": 845800,
      "sellPriceFormatted": "Rp 845.800",
      "pricePerGram": 3383200,
      "pricePerGramFormatted": "Rp 3.383.200/gram"
    },
    {
      "weight": 0.1,
      "weightUnit": "gram",
      "type": "Antam 0.1g",
      "sellPrice": 363900,
      "sellPriceFormatted": "Rp 363.900",
      "pricePerGram": 3639000,
      "pricePerGramFormatted": "Rp 3.639.000/gram"
    }
  ]
}