{
  "source": "harga-emas.org",
  "url": "https://harga-emas.org",
  "scrapedAt": "2026-02-05T09:38:33.129Z",
  "updateTime": "05 Februari 2026",
  "buybackPrice": {
    "price": 2795400,
    "priceFormatted": "Rp 2.795.400",
    "type": "Buyback per gram"
  },
  "antam": [
    {
      "weight": 100,
      "weightUnit": "gram",
      "type": "Antam 100g",
      "sellPrice": 283721000,
      "sellPriceFormatted": "Rp 283.721.000",
      "pricePerGram": 2837210,
      "pricePerGramFormatted": "Rp 2.837.210/gram"
    },
    {
      "weight": 50,
      "weightUnit": "gram",
      "type": "Antam 50g",
      "sellPrice": 142350000,
      "sellPriceFormatted": "Rp 142.350.000",
      "pricePerGram": 2847000,
      "pricePerGramFormatted": "Rp 2.847.000/gram"
    },
    {
      "weight": 25,
      "weightUnit": "gram",
      "type": "Antam 25g",
      "sellPrice": 71309000,
      "sellPriceFormatted": "Rp 71.309.000",
      "pricePerGram": 2852360,
      "pricePerGramFormatted": "Rp 2.852.360/gram"
    },
    {
      "weight": 10,
      "weightUnit": "gram",
      "type": "Antam 10g",
      "sellPrice": 28571000,
      "sellPriceFormatted": "Rp 28.571.000",
      "pricePerGram": 2857100,
      "pricePerGramFormatted": "Rp 2.857.100/gram"
    },
    {
      "weight": 7,
      "weightUnit": "gram",
      "type": "Antam 7g",
      "sellPrice": 30060000,
      "sellPriceFormatted": "Rp 30.060.000",
      "pricePerGram": 4294286,
      "pricePerGramFormatted": "Rp 4.294.286/gram"
    },
    {
      "weight": 5,
      "weightUnit": "gram",
      "type": "Antam 5g",
      "sellPrice": 14357000,
      "sellPriceFormatted": "Rp 14.357.000",
      "pricePerGram": 2871400,
      "pricePerGramFormatted": "Rp 2.871.400/gram"
    },
    {
      "weight": 4,
      "weightUnit": "gram",
      "type": "Antam 4g",
      "sellPrice": 11570500,
      "sellPriceFormatted": "Rp 11.570.500",
      "pricePerGram": 2892625,
      "pricePerGramFormatted": "Rp 2.892.625/gram"
    },
    {
      "weight": 3,
      "weightUnit": "gram",
      "type": "Antam 3g",
      "sellPrice": 8695500,
      "sellPriceFormatted": "Rp 8.695.500",
      "pricePerGram": 2898500,
      "pricePerGramFormatted": "Rp 2.898.500/gram"
    },
    {
      "weight": 2,
      "weightUnit": "gram",
      "type": "Antam 2g",
      "sellPrice": 7400000,
      "sellPriceFormatted": "Rp 7.400.000",
      "pricePerGram": 3700000,
      "pricePerGramFormatted": "Rp 3.700.000/gram"
    },
    {
      "weight": 1,
      "weightUnit": "gram",
      "type": "Antam 1g",
      "sellPrice": 3700000,
      "sellPriceFormatted": "Rp 3.700.000",
      "pricePerGram": 3700000,
      "pricePerGramFormatted": "Rp 3.700.000/gram"
    },
    {
      "weight": 0.5,
      "weightUnit": "gram",
      "type": "Antam 0.5g",
      "sellPrice": 1551500,
      "sellPriceFormatted": "Rp 1.551.500",
      "pricePerGram": 3103000,
      "pricePerGramFormatted": "Rp 3.103.000/gram"
    },
    {
      "weight": 0.25,
      "weightUnit": "gram",
      "type": "Antam 0.25g",
      "sellPrice": 840300,
      "sellPriceFormatted": "Rp 840.300",
      "pricePerGram": 3361200,
      "pricePerGramFormatted": "Rp 3.361.200/gram"
    },
    {
      "weight": 0.1,
      "weightUnit": "gram",
      "type": "Antam 0.1g",
      "sellPrice": 361700,
      "sellPriceFormatted": "Rp 361.700",
      "pricePerGram": 3617000,
      "pricePerGramFormatted": "Rp 3.617.000/gram"
    }
  ]
}